.gitignore
README.rst
RELEASE-VERSION
setup.py
django_package_skeleton.egg-info/PKG-INFO
django_package_skeleton.egg-info/SOURCES.txt
django_package_skeleton.egg-info/dependency_links.txt
django_package_skeleton.egg-info/requires.txt
django_package_skeleton.egg-info/top_level.txt
docs/Makefile
docs/conf.py
docs/index.rst
docs/make.bat
package/__init__.py
package/tests/__init__.py
package/tests/app_testcase.py
packageutils/__init__.py
packageutils/runtests.py
packageutils/version.py
tests/__init__.py
tests/manage.py
tests/settings.py
tests/urls.py
tests/blogs/__init__.py
tests/blogs/forms.py
tests/blogs/models.py
tests/blogs/urls.py
tests/blogs/views.py
tests/blogs/fixtures/test.yaml
tests/blogs/templates/404.html
tests/blogs/templates/blog/entry_confirm_delete.html
tests/blogs/templates/blog/entry_detail.html
tests/blogs/templates/blog/entry_form.html
tests/blogs/templates/blog/entry_list.html
tests/blogs/tests/__init__.py
tests/blogs/tests/test_models.py
tests/blogs/tests/test_views.py
tests/static/css/style.css
tests/static/css/style.scss
tests/static/css/image/edit.png
tests/static/css/image/trash.png
tests/templates/404.html
tests/templates/base.html
tests/templates/blogs/entry_confirm_delete.html
tests/templates/blogs/entry_detail.html
tests/templates/blogs/entry_form.html
tests/templates/blogs/entry_list.html
tests/templates/registration/logged_out.html
tests/templates/registration/login.html